ORTipy/__init__.py
ORTipy/gomory_ilpp.py
ORTipy/graphical_lpp.py
ORTipy/perturbation_method.py
ORTipy/simplex_lpp.py
ORTipy-0.1.dist-info/LICENSE
ORTipy-0.1.dist-info/METADATA
ORTipy-0.1.dist-info/WHEEL
ORTipy-0.1.dist-info/top_level.txt
ORTipy-0.1.dist-info/RECORD
